pyke/__init__.py
pyke/_version.py
pyke/action.py
pyke/ansi.py
pyke/config.py
pyke/options.py
pyke/options_parser.py
pyke/pyke-config.json
pyke/pyke.py
pyke/utilities.py
pyke/phases/__init__.py
pyke/phases/archive.py
pyke/phases/c_family_build.py
pyke/phases/command_phase.py
pyke/phases/compile.py
pyke/phases/compile_and_archive.py
pyke/phases/compile_and_link_to_exe.py
pyke/phases/compile_and_link_to_so.py
pyke/phases/link_to_exe.py
pyke/phases/link_to_shared_object.py
pyke/phases/phase.py
pyke/phases/project.py
pyke_build-0.2.1.dist-info/LICENSE
pyke_build-0.2.1.dist-info/METADATA
pyke_build-0.2.1.dist-info/WHEEL
pyke_build-0.2.1.dist-info/entry_points.txt
pyke_build-0.2.1.dist-info/top_level.txt
pyke_build-0.2.1.dist-info/RECORD
