Metadata-Version: 2.1
Name: pyke-build
Version: 0.2.1
Summary: A python-based build system for automating build and deployment tasks.
Author-email: Trevor Schrock <spacemeat@gmail.com>
Maintainer-email: Trevor Schrock <spacemeat@gmail.com>
License: MIT License
Project-URL: Repository, https://github.com/spacemeat/pyke.git
Keywords: C,C++,build
Classifier: Development Status :: 3 - Alpha
Classifier: Intended Audience :: Developers
Classifier: Programming Language :: Python :: 3.10
Classifier: Programming Language :: C
Classifier: Programming Language :: C++
Classifier: Environment :: Console
Classifier: License :: OSI Approved :: MIT License
Classifier: Topic :: Software Development :: Build Tools
Requires-Python: >=3.10
License-File: LICENSE
Requires-Dist: typing-extensions ==4.9.0
